SeriesDeTiempo/__init__.py
SeriesDeTiempo/brown.py
SeriesDeTiempo/descomposicion.py
SeriesDeTiempo/holt.py
SeriesDeTiempo/holtYWinters.py
SeriesDeTiempo/mediaMovilDoble.py
SeriesDeTiempo/mediaMovilDobleConTendencia.py
SeriesDeTiempo/mediaMovilPonderada.py
SeriesDeTiempo/mediaMovilSimple.py
SeriesDeTiempo/naive.py
SeriesDeTiempo/pruebas.py
SeriesDeTiempo/serie.py
SeriesDeTiempo/suavizacionExponencialSimple.py
series_de_tiempo_pabloatarama-2021.12.1.dist-info/LICENSE
series_de_tiempo_pabloatarama-2021.12.1.dist-info/METADATA
series_de_tiempo_pabloatarama-2021.12.1.dist-info/WHEEL
series_de_tiempo_pabloatarama-2021.12.1.dist-info/top_level.txt
series_de_tiempo_pabloatarama-2021.12.1.dist-info/RECORD
