Metadata-Version: 2.1
Name: series-de-tiempo-pabloatarama
Version: 2021.12.1
Summary: Modelos para el análisis de series de tiempo y proyecciones.
Home-page: https://pabloatarama.com/SeriesDeTiempo/
Author: Pablo Atarama
Author-email: contacto@pabloatarama.com
License: UNKNOWN
Platform: UNKNOWN
License-File: LICENSE
